LICENSE.txt
MANIFEST.in
README.rst
requirements.txt
setup.py
test-requirements.txt
pywbemReq/__init__.py
pywbemReq/cim_constants.py
pywbemReq/cim_http.py
pywbemReq/cim_obj.py
pywbemReq/cim_operations.py
pywbemReq/cim_provider.py
pywbemReq/cim_provider2.py
pywbemReq/cim_types.py
pywbemReq/cim_xml.py
pywbemReq/cimxml_parse.py
pywbemReq/tupleparse.py
pywbemReq/tupletree.py
pywbemReq/wbemcli.py
pywbemReq.egg-info/PKG-INFO
pywbemReq.egg-info/SOURCES.txt
pywbemReq.egg-info/dependency_links.txt
pywbemReq.egg-info/requires.txt
pywbemReq.egg-info/top_level.txt