Metadata-Version: 1.1
Name: pywbemReq
Version: 0.0.2
Summary: Fork of pywbem that only including requests.
Home-page: UNKNOWN
Author: Cedric Zhuang
Author-email: cedric.zhuang@gmail.com
License: LGPLv2+
Keywords: pywbem,SMI-S
Platform: any
Classifier: Programming Language :: Python
Classifier: Programming Language :: Python :: 2.7
Classifier: Programming Language :: Python :: 3.4
Classifier: Programming Language :: Python :: 3.5
Classifier: Natural Language :: English
Classifier: Intended Audience :: Developers
Classifier: Operating System :: OS Independent
Classifier: Development Status :: 4 - Beta
Classifier: Topic :: Utilities
Classifier: License :: OSI Approved :: GNU Lesser General Public License v2 or later (LGPLv2+)
